dsnd_probability_M3hzhats/Binomialdistribution.py
dsnd_probability_M3hzhats/Gaussiandistribution.py
dsnd_probability_M3hzhats/Generaldistribution.py
dsnd_probability_M3hzhats/__init__.py
dsnd_probability_M3hzhats-0.6.dist-info/METADATA
dsnd_probability_M3hzhats-0.6.dist-info/WHEEL
dsnd_probability_M3hzhats-0.6.dist-info/top_level.txt
dsnd_probability_M3hzhats-0.6.dist-info/RECORD
