Metadata-Version: 2.1
Name: dsnd-probability-M3hzhats
Version: 0.6
Summary: Gaussian and Binomial distributions
Author-email: maria.j.19@hotmail.com
License: UNKNOWN
Platform: UNKNOWN
Requires-Dist: matplotlib
